wide_analysis/__init__.py
wide_analysis/analyze.py
wide_analysis/data_collect.py
wide_analysis/asset/Wide_Analysis_overall.png
wide_analysis/data/__init__.py
wide_analysis/data/collect_data.py
wide_analysis/data/collect_data_es.py
wide_analysis/data/collect_data_gr.py
wide_analysis/data/collect_data_new.py
wide_analysis/data/collect_data_wikidata_ent.py
wide_analysis/data/collect_data_wikidata_prop.py
wide_analysis/data/collect_data_wikinews.py
wide_analysis/data/collect_data_wikiquote.py
wide_analysis/data/process_data.py
wide_analysis/model/__init__.py
wide_analysis/model/offensive.py
wide_analysis/model/outcome.py
wide_analysis/model/policy.py
wide_analysis/model/sentiment.py
wide_analysis/model/stance.py
wide_analysis/utils/__init__.py
wide_analysis/utils/collect_editor_stats.py
wide_analysis/utils/helper.py
wide_analysis-1.2.11.dist-info/LICENSE
wide_analysis-1.2.11.dist-info/METADATA
wide_analysis-1.2.11.dist-info/WHEEL
wide_analysis-1.2.11.dist-info/entry_points.txt
wide_analysis-1.2.11.dist-info/top_level.txt
wide_analysis-1.2.11.dist-info/RECORD
