Metadata-Version: 2.1
Name: wide-analysis
Version: 1.2.11
Summary: A package for analyzing deletion discussions of Wiki platforms.
Home-page: UNKNOWN
Author: Anonymous author
Author-email: boyanonymus@gmail.com
License: UNKNOWN
Platform: UNKNOWN
Classifier: Programming Language :: Python :: 3
Classifier: License :: OSI Approved :: MIT License
Classifier: Operating System :: OS Independent
Requires-Python: >=3.6
License-File: LICENSE
Requires-Dist: beautifulsoup4
Requires-Dist: datasets
Requires-Dist: openai
Requires-Dist: pandas
Requires-Dist: pysbd
Requires-Dist: requests
Requires-Dist: tiktoken
Requires-Dist: torch
Requires-Dist: transformers
